[
  {"story_id": 100, "section_id": 1, "chara_id": 2, "chapter_id": "1",
   "next_chapter_id": "2", "required_chapter_id": null,
   "selection_display_position": null, "selection_text_id": null,
   "show_coordinate": 1, "x_coordinate": 100, "y_coordinate": -100,
   "is_camera_movable": 1, "show_subtitles": 0,
   "battle_exists": true, "enemy_chara_id": 500010, "enemy_class": 2, "enemy_ai_id": 2001,
   "bg_file_name": "6", "chapter_effect_path": null, "chapter_clear_text_id": null,
   "battle3dfield_id": 4, "bgm_id": "0", "special_battle_setting_id": null,
   "release_point": 0, "is_maintenance_chapter": false,
   "is_play_another_end_appearance_animation": false, "is_released_another_end": false,
   "is_skip_enabled": true,
   "battle_settings": [{"deck_class_id": 2, "player_emotion_override": 0,
     "enemy_emotion_override": 0, "skin_id_override": 0, "battle3dfield_id_override": 0,
     "bgm_id_override": 0, "deck_skin_id_override": 0}],
   "story_reward": [{"reward_type": 5, "reward_detail_id": 100222010, "reward_number": 3}],
   "sub_chapters": []},
  {"story_id": 101, "section_id": 1, "chara_id": 2, "chapter_id": "2",
   "next_chapter_id": "3", "required_chapter_id": null,
   "selection_display_position": null, "selection_text_id": null,
   "show_coordinate": 1, "x_coordinate": 200, "y_coordinate": -100,
   "is_camera_movable": 1, "show_subtitles": 0,
   "battle_exists": true, "enemy_chara_id": 6, "enemy_class": 6, "enemy_ai_id": 2002,
   "bg_file_name": "4", "chapter_effect_path": null, "chapter_clear_text_id": null,
   "battle3dfield_id": 2, "bgm_id": "0", "special_battle_setting_id": 8,
   "release_point": 0, "is_maintenance_chapter": false,
   "is_play_another_end_appearance_animation": false, "is_released_another_end": false,
   "is_skip_enabled": true,
   "battle_settings": [{"deck_class_id": 2, "player_emotion_override": 0,
     "enemy_emotion_override": 0, "skin_id_override": 0, "battle3dfield_id_override": 0,
     "bgm_id_override": 0, "deck_skin_id_override": 0}],
   "story_reward": [{"reward_type": 1, "reward_detail_id": 0, "reward_number": 20}],
   "sub_chapters": []}
]
